bfg/__init__.py
bfg/breakers.py
bfg/data.py
bfg/defaults.py
bfg/errors.py
bfg/module.py
bfg/yaml_models.py
bfg/args/__init__.py
bfg/args/http.py
bfg/args/testing.py
bfg/cli/__init__.py
bfg/cli/manage_db.py
bfg/datasets/__init__.py
bfg/datasets/azure_sso_soap.xml
bfg/datasets/ua_strings.txt
bfg/modules/__init__.py
bfg/modules/http/__init__.py
bfg/modules/http/accellion_ftp/__init__.py
bfg/modules/http/accellion_ftp/module.py
bfg/modules/http/adfs/__init__.py
bfg/modules/http/adfs/module.py
bfg/modules/http/azure_ad_seamless_sso/__init__.py
bfg/modules/http/azure_ad_seamless_sso/module.py
bfg/modules/http/azure_blender/__init__.py
bfg/modules/http/azure_blender/module.py
bfg/modules/http/basic_digest/__init__.py
bfg/modules/http/basic_digest/module.py
bfg/modules/http/basic_ntlm/__init__.py
bfg/modules/http/basic_ntlm/module.py
bfg/modules/http/cisco_ssl_vpn/__init__.py
bfg/modules/http/cisco_ssl_vpn/module.py
bfg/modules/http/global_protect/__init__.py
bfg/modules/http/global_protect/module.py
bfg/modules/http/lync/__init__.py
bfg/modules/http/lync/module.py
bfg/modules/http/mattermost/__init__.py
bfg/modules/http/mattermost/module.py
bfg/modules/http/ms_graph/__init__.py
bfg/modules/http/ms_graph/module.py
bfg/modules/http/netwrix/__init__.py
bfg/modules/http/netwrix/module.py
bfg/modules/http/okta/__init__.py
bfg/modules/http/okta/module.py
bfg/modules/http/owa2010/__init__.py
bfg/modules/http/owa2010/module.py
bfg/modules/http/owa2016/__init__.py
bfg/modules/http/owa2016/module.py
bfg/modules/http/sap_webdynpro/__init__.py
bfg/modules/http/sap_webdynpro/module.py
bfg/modules/smb/__init__.py
bfg/modules/smb/smb/__init__.py
bfg/modules/smb/smb/module.py
bfg/modules/testing/__init__.py
bfg/modules/testing/fake/__init__.py
bfg/modules/testing/fake/module.py
bfg/modules/testing/fake_lockouts/__init__.py
bfg/modules/testing/fake_lockouts/module.py
bfg/shortcuts/__init__.py
bfg/shortcuts/azure.py
bfg/shortcuts/http.py
bl_bfg-1.0.4.data/scripts/bfg
bl_bfg-1.0.4.dist-info/LICENSE
bl_bfg-1.0.4.dist-info/METADATA
bl_bfg-1.0.4.dist-info/WHEEL
bl_bfg-1.0.4.dist-info/top_level.txt
bl_bfg-1.0.4.dist-info/RECORD
