Metadata-Version: 2.1
Name: bl-bfg
Version: 1.0.4
Summary: A password guessing framework.
Home-page: https://github.com/arch4ngel/bl-bfg
Author: Justin Angel
Author-email: justin@arch4ngel.ninja
Classifier: Programming Language :: Python :: 3
Classifier: License :: OSI Approved :: MIT License
Classifier: Operating System :: POSIX :: Linux
Requires-Python: >=3.9.2
License-File: LICENSE
Requires-Dist: bruteloops >=1
Requires-Dist: requests-ntlm ==1.1.0
Requires-Dist: pysmb ==1.1.27
Requires-Dist: lxml >=4.6.4
Requires-Dist: pyyaml
Requires-Dist: xmltodict
Requires-Dist: dict-toolbox
Requires-Dist: pydantic ==1.10.12
